plater/__init__.py
plater/cli.py
plater/plater.py
plater/templates.py
test/__init__.py
test/test_cli.py
plater-0.4.dist-info/LICENSE
plater-0.4.dist-info/METADATA
plater-0.4.dist-info/WHEEL
plater-0.4.dist-info/entry_points.txt
plater-0.4.dist-info/top_level.txt
plater-0.4.dist-info/RECORD
