Metadata-Version: 2.1
Name: plater
Version: 0.4
Summary: Easily create a starter file template for different project
Home-page: https://github.com/aquadzn/plater
Author: William Jacques
Author-email: williamjcqs8@gmail.com
License: UNKNOWN
Platform: UNKNOWN
Classifier: Programming Language :: Python :: 3
Classifier: License :: OSI Approved :: MIT License
Classifier: Operating System :: OS Independent
Requires-Python: >=3.6
